Workbook

Sheet README
A1: AI Video — cost and pricing model
A4: SHEET | B4: WHAT IT HOLDS
A5: Assumptions | B5: Every input in one place — FX, provider rates, video profile, markup. Yellow = editable.
A6: Unit COGS | B6: One row per provider call, mapped to its call site in src/. Costs are formulas.
A7: Per Video | B7: Build-up of one finished video, first pass and with realistic rework.
A8: Credits | B8: The credit price list, with margin per action and the never-metered list.
A9: Plans | B9: Plan pricing and margin at both 100% and expected credit burn.
A10: Fixed Costs | B10: Monthly infrastructure and the fixed cost per paying user.
A11: P&L | B11: Monthly scenario by user mix, with break-even.
A12: Optimisations | B12: Cost cuts available before launch, quantified.
A13: User-Facing | B13: The surface: what the customer sees, and the UI rules for showing it.
A16: Verify first: | B16: gemini-3.1-flash-tts-preview pricing is an estimate on a preview model, and it drives 74% of voiceover cost. Confirm the rate and GA timeline before committing to the 3-credits-per-15s number.
A18: Source: | B18: Web Application/docs/pricing-and-credits.md — same model in prose, with the Prisma schema and charging rules.

Sheet Assumptions
A1: Assumptions
A2: Yellow cells are inputs — change these and every other sheet re-costs. Verify provider rates before launch.
A4: GLOBAL
A5: USD → INR | B5: 88 | F5: Update to the live rate before pricing decisions.
A6: GST rate on your sale | B6: 0.18 | F6: 18% SaaS GST. Plan prices below are GST-inclusive.
A7: Payment gateway fee | B7: 0.0236 | F7: Razorpay 2% + 18% GST on the fee.
A8: Credit value (₹ per credit) | B8: 1 | F8: 1 credit = ₹1 of retail value. Keeps pricing legible.
A9: Audio tokens per second | B9: 32 | F9: Gemini audio tokenisation rate. Drives TTS + STT cost.
A10: Reference video length (sec) | B10: 45 | F10: Drives voiceover cost and credits.
A11: Photos per project | B11: 15 | F11: Drives photo-analysis cost.
A13: PROVIDER RATES (USD per 1M tokens)
A14: Model | B14: Text in | C14: Text out | D14: Audio in | E14: Audio out | F14: Notes
A15: gpt-4o | B15: 2.5 | C15: 10 | D15: 0 | E15: 0 | F15: Vision images billed as input tokens (~765 tok @1024px).
A16: gpt-4o-mini | B16: 0.15 | C16: 0.6 | D16: 0 | E16: 0 | F16: Vision uses ~2,833 tok/image but is still ~7x cheaper.
A17: gemini-2.5-flash | B17: 0.3 | C17: 2.5 | D17: 1 | E17: 0 | F17: Text gen, TTS normalisation, and STT alignment.
A18: gemini-tts | B18: 0.5 | C18: 0 | D18: 0 | E18: 10 | F18: gemini-3.1-flash-tts-preview — PREVIEW PRICING, VERIFY.
A19: none | B19: 0 | C19: 0 | D19: 0 | E19: 0 | F19: For rows costed directly in USD (render, storage).
A21: PRICING POLICY
A22: Target markup on COGS | B22: 3.8 | F22: Credits are priced at ~3.8x underlying cost.
A23: Expected credit burn rate | B23: 0.65 | F23: Share of granted credits actually spent in a month.
A24: Paying users (for fixed-cost split) | B24: 200 | F24: Used on Fixed Costs and P&L sheets.

Sheet Unit COGS
A1: Unit COGS — cost of every provider call
A2: One row per API call, grouped by the user action that triggers it. Cost formulas read the rate table on Assumptions.
A4: Action | B4: Step / call site | C4: Model | D4: Text in (tok) | E4: Text out (tok) | F4: Audio in (sec) | G4: Audio out (sec) | H4: Direct $ | I4: USD | J4: INR
A5: Extract facts | B5: extract-facts.ts | C5: gpt-4o | D5: 1200 | E5: 400 | F5: 0 | G5: 0 | H5: 0 | I5: =(D5*VLOOKUP($C5,Assumptions!$A$15:$E$19,2,FALSE)+E5*VLOOKUP($C5,Assumptions!$A$15:$E$19,3,FALSE)+F5*Assumptions!$B$9*VLOOKUP($C5,Assumptions!$A$15:$E$19,4,FALSE)+G5*Assumptions!$B$9*VLOOKUP($C5,Assumptions!$A$15:$E$19,5,FALSE))/1000000+H5 | J5: =I5*Assumptions!$B$5
A6: Script pack | B6: generate-script — 3 variations | C6: gemini-2.5-flash | D6: 3900 | E6: 660 | F6: 0 | G6: 0 | H6: 0 | I6: =(D6*VLOOKUP($C6,Assumptions!$A$15:$E$19,2,FALSE)+E6*VLOOKUP($C6,Assumptions!$A$15:$E$19,3,FALSE)+F6*Assumptions!$B$9*VLOOKUP($C6,Assumptions!$A$15:$E$19,4,FALSE)+G6*Assumptions!$B$9*VLOOKUP($C6,Assumptions!$A$15:$E$19,5,FALSE))/1000000+H6 | J6: =I6*Assumptions!$B$5
A7: Refine script | B7: refine-script | C7: gemini-2.5-flash | D7: 1500 | E7: 250 | F7: 0 | G7: 0 | H7: 0 | I7: =(D7*VLOOKUP($C7,Assumptions!$A$15:$E$19,2,FALSE)+E7*VLOOKUP($C7,Assumptions!$A$15:$E$19,3,FALSE)+F7*Assumptions!$B$9*VLOOKUP($C7,Assumptions!$A$15:$E$19,4,FALSE)+G7*Assumptions!$B$9*VLOOKUP($C7,Assumptions!$A$15:$E$19,5,FALSE))/1000000+H7 | J7: =I7*Assumptions!$B$5
A8: Photo analysis | B8: analyze-image.ts — vision, per image | C8: gpt-4o | D8: 965 | E8: 150 | F8: 0 | G8: 0 | H8: 0 | I8: =(D8*VLOOKUP($C8,Assumptions!$A$15:$E$19,2,FALSE)+E8*VLOOKUP($C8,Assumptions!$A$15:$E$19,3,FALSE)+F8*Assumptions!$B$9*VLOOKUP($C8,Assumptions!$A$15:$E$19,4,FALSE)+G8*Assumptions!$B$9*VLOOKUP($C8,Assumptions!$A$15:$E$19,5,FALSE))/1000000+H8 | J8: =I8*Assumptions!$B$5
A9: Voiceover | B9: Normalisation ×2 (non-English path) | C9: gemini-2.5-flash | D9: 1400 | E9: 500 | F9: 0 | G9: 0 | H9: 0 | I9: =(D9*VLOOKUP($C9,Assumptions!$A$15:$E$19,2,FALSE)+E9*VLOOKUP($C9,Assumptions!$A$15:$E$19,3,FALSE)+F9*Assumptions!$B$9*VLOOKUP($C9,Assumptions!$A$15:$E$19,4,FALSE)+G9*Assumptions!$B$9*VLOOKUP($C9,Assumptions!$A$15:$E$19,5,FALSE))/1000000+H9 | J9: =I9*Assumptions!$B$5
A10: Voiceover | B10: Gemini TTS synthesis | C10: gemini-tts | D10: 450 | E10: 0 | F10: 0 | G10: =Assumptions!$B$10 | H10: 0 | I10: =(D10*VLOOKUP($C10,Assumptions!$A$15:$E$19,2,FALSE)+E10*VLOOKUP($C10,Assumptions!$A$15:$E$19,3,FALSE)+F10*Assumptions!$B$9*VLOOKUP($C10,Assumptions!$A$15:$E$19,4,FALSE)+G10*Assumptions!$B$9*VLOOKUP($C10,Assumptions!$A$15:$E$19,5,FALSE))/1000000+H10 | J10: =I10*Assumptions!$B$5
A11: Voiceover | B11: STT word alignment | C11: gemini-2.5-flash | D11: 600 | E11: 700 | F11: =Assumptions!$B$10 | G11: 0 | H11: 0 | I11: =(D11*VLOOKUP($C11,Assumptions!$A$15:$E$19,2,FALSE)+E11*VLOOKUP($C11,Assumptions!$A$15:$E$19,3,FALSE)+F11*Assumptions!$B$9*VLOOKUP($C11,Assumptions!$A$15:$E$19,4,FALSE)+G11*Assumptions!$B$9*VLOOKUP($C11,Assumptions!$A$15:$E$19,5,FALSE))/1000000+H11 | J11: =I11*Assumptions!$B$5
A12: Voice preview | B12: 10s sample, TTS only | C12: gemini-tts | D12: 200 | E12: 0 | F12: 0 | G12: 10 | H12: 0 | I12: =(D12*VLOOKUP($C12,Assumptions!$A$15:$E$19,2,FALSE)+E12*VLOOKUP($C12,Assumptions!$A$15:$E$19,3,FALSE)+F12*Assumptions!$B$9*VLOOKUP($C12,Assumptions!$A$15:$E$19,4,FALSE)+G12*Assumptions!$B$9*VLOOKUP($C12,Assumptions!$A$15:$E$19,5,FALSE))/1000000+H12 | J12: =I12*Assumptions!$B$5
A13: Subtitle re-align | B13: STT only, no new audio | C13: gemini-2.5-flash | D13: 600 | E13: 700 | F13: =Assumptions!$B$10 | G13: 0 | H13: 0 | I13: =(D13*VLOOKUP($C13,Assumptions!$A$15:$E$19,2,FALSE)+E13*VLOOKUP($C13,Assumptions!$A$15:$E$19,3,FALSE)+F13*Assumptions!$B$9*VLOOKUP($C13,Assumptions!$A$15:$E$19,4,FALSE)+G13*Assumptions!$B$9*VLOOKUP($C13,Assumptions!$A$15:$E$19,5,FALSE))/1000000+H13 | J13: =I13*Assumptions!$B$5
A14: Subtitle translate | B14: subtitles/translate | C14: gpt-4o | D14: 1500 | E14: 900 | F14: 0 | G14: 0 | H14: 0 | I14: =(D14*VLOOKUP($C14,Assumptions!$A$15:$E$19,2,FALSE)+E14*VLOOKUP($C14,Assumptions!$A$15:$E$19,3,FALSE)+F14*Assumptions!$B$9*VLOOKUP($C14,Assumptions!$A$15:$E$19,4,FALSE)+G14*Assumptions!$B$9*VLOOKUP($C14,Assumptions!$A$15:$E$19,5,FALSE))/1000000+H14 | J14: =I14*Assumptions!$B$5
A15: AI auto-edit | B15: timeline/generate — generate-ai.ts | C15: gpt-4o | D15: 3000 | E15: 2000 | F15: 0 | G15: 0 | H15: 0 | I15: =(D15*VLOOKUP($C15,Assumptions!$A$15:$E$19,2,FALSE)+E15*VLOOKUP($C15,Assumptions!$A$15:$E$19,3,FALSE)+F15*Assumptions!$B$9*VLOOKUP($C15,Assumptions!$A$15:$E$19,4,FALSE)+G15*Assumptions!$B$9*VLOOKUP($C15,Assumptions!$A$15:$E$19,5,FALSE))/1000000+H15 | J15: =I15*Assumptions!$B$5
A16: Social captions | B16: generate-social + titles | C16: gpt-4o | D16: 1200 | E16: 500 | F16: 0 | G16: 0 | H16: 0 | I16: =(D16*VLOOKUP($C16,Assumptions!$A$15:$E$19,2,FALSE)+E16*VLOOKUP($C16,Assumptions!$A$15:$E$19,3,FALSE)+F16*Assumptions!$B$9*VLOOKUP($C16,Assumptions!$A$15:$E$19,4,FALSE)+G16*Assumptions!$B$9*VLOOKUP($C16,Assumptions!$A$15:$E$19,5,FALSE))/1000000+H16 | J16: =I16*Assumptions!$B$5
A17: Web export | B17: Remotion/FFmpeg render worker | C17: none | D17: 0 | E17: 0 | F17: 0 | G17: 0 | H17: 0.013636 | I17: =(D17*VLOOKUP($C17,Assumptions!$A$15:$E$19,2,FALSE)+E17*VLOOKUP($C17,Assumptions!$A$15:$E$19,3,FALSE)+F17*Assumptions!$B$9*VLOOKUP($C17,Assumptions!$A$15:$E$19,4,FALSE)+G17*Assumptions!$B$9*VLOOKUP($C17,Assumptions!$A$15:$E$19,5,FALSE))/1000000+H17 | J17: =I17*Assumptions!$B$5
A18: Storage | B18: R2, ~75MB, 6-month retention | C18: none | D18: 0 | E18: 0 | F18: 0 | G18: 0 | H18: 0.011364 | I18: =(D18*VLOOKUP($C18,Assumptions!$A$15:$E$19,2,FALSE)+E18*VLOOKUP($C18,Assumptions!$A$15:$E$19,3,FALSE)+F18*Assumptions!$B$9*VLOOKUP($C18,Assumptions!$A$15:$E$19,4,FALSE)+G18*Assumptions!$B$9*VLOOKUP($C18,Assumptions!$A$15:$E$19,5,FALSE))/1000000+H18 | J18: =I18*Assumptions!$B$5
A19: Photo analysis (4o-mini alt) | B19: Same call on gpt-4o-mini — comparison only | C19: gpt-4o-mini | D19: 3033 | E19: 150 | F19: 0 | G19: 0 | H19: 0 | I19: =(D19*VLOOKUP($C19,Assumptions!$A$15:$E$19,2,FALSE)+E19*VLOOKUP($C19,Assumptions!$A$15:$E$19,3,FALSE)+F19*Assumptions!$B$9*VLOOKUP($C19,Assumptions!$A$15:$E$19,4,FALSE)+G19*Assumptions!$B$9*VLOOKUP($C19,Assumptions!$A$15:$E$19,5,FALSE))/1000000+H19 | J19: =I19*Assumptions!$B$5
A21: COST PER USER ACTION (sum of its calls)
A22: Action | B22: INR
A23: Extract facts | B23: =SUMIF($A$5:$A$19,A23,$J$5:$J$19)
A24: Script pack | B24: =SUMIF($A$5:$A$19,A24,$J$5:$J$19)
A25: Refine script | B25: =SUMIF($A$5:$A$19,A25,$J$5:$J$19)
A26: Photo analysis | B26: =SUMIF($A$5:$A$19,A26,$J$5:$J$19)
A27: Voiceover | B27: =SUMIF($A$5:$A$19,A27,$J$5:$J$19)
A28: Voice preview | B28: =SUMIF($A$5:$A$19,A28,$J$5:$J$19)
A29: Subtitle re-align | B29: =SUMIF($A$5:$A$19,A29,$J$5:$J$19)
A30: Subtitle translate | B30: =SUMIF($A$5:$A$19,A30,$J$5:$J$19)
A31: AI auto-edit | B31: =SUMIF($A$5:$A$19,A31,$J$5:$J$19)
A32: Social captions | B32: =SUMIF($A$5:$A$19,A32,$J$5:$J$19)
A33: Web export | B33: =SUMIF($A$5:$A$19,A33,$J$5:$J$19)
A34: Storage | B34: =SUMIF($A$5:$A$19,A34,$J$5:$J$19)
A35: Photo analysis (4o-mini alt) | B35: =SUMIF($A$5:$A$19,A35,$J$5:$J$19)
A37: Voiceover scales with duration — at the reference length it is ~74% TTS audio output, 17% alignment, 9% normalisation.

Sheet Per Video
A1: Cost of one finished video
A2: First pass = everything generated once. Realistic = the back-and-forth users actually do.
A4: Line item | B4: Unit COGS ₹ | C4: Qty (first pass) | D4: First pass ₹ | E4: Qty (realistic) | F4: Realistic ₹ | G4: Credits each | H4: Credits (realistic)
A5: Extract facts | B5: =VLOOKUP(A5,'Unit COGS'!$A$23:$B$35,2,FALSE) | C5: 1 | D5: =B5*C5 | E5: 1 | F5: =B5*E5 | G5: =VLOOKUP(A5,Credits!$A$5:$C$17,3,FALSE) | H5: =E5*G5
A6: Script pack | B6: =VLOOKUP(A6,'Unit COGS'!$A$23:$B$35,2,FALSE) | C6: 1 | D6: =B6*C6 | E6: 2 | F6: =B6*E6 | G6: =VLOOKUP(A6,Credits!$A$5:$C$17,3,FALSE) | H6: =E6*G6
A7: Refine script | B7: =VLOOKUP(A7,'Unit COGS'!$A$23:$B$35,2,FALSE) | C7: 0 | D7: =B7*C7 | E7: 1 | F7: =B7*E7 | G7: =VLOOKUP(A7,Credits!$A$5:$C$17,3,FALSE) | H7: =E7*G7
A8: Photo analysis | B8: =VLOOKUP(A8,'Unit COGS'!$A$23:$B$35,2,FALSE) | C8: =Assumptions!$B$11 | D8: =B8*C8 | E8: =Assumptions!$B$11 | F8: =B8*E8 | G8: =VLOOKUP(A8,Credits!$A$5:$C$17,3,FALSE) | H8: =E8*G8
A9: Voice preview | B9: =VLOOKUP(A9,'Unit COGS'!$A$23:$B$35,2,FALSE) | C9: 0 | D9: =B9*C9 | E9: 3 | F9: =B9*E9 | G9: =VLOOKUP(A9,Credits!$A$5:$C$17,3,FALSE) | H9: =E9*G9
A10: Voiceover | B10: =VLOOKUP(A10,'Unit COGS'!$A$23:$B$35,2,FALSE) | C10: 1 | D10: =B10*C10 | E10: 2 | F10: =B10*E10 | G10: =VLOOKUP(A10,Credits!$A$5:$C$17,3,FALSE) | H10: =E10*G10
A11: AI auto-edit | B11: =VLOOKUP(A11,'Unit COGS'!$A$23:$B$35,2,FALSE) | C11: 1 | D11: =B11*C11 | E11: 1 | F11: =B11*E11 | G11: =VLOOKUP(A11,Credits!$A$5:$C$17,3,FALSE) | H11: =E11*G11
A12: Subtitle re-align | B12: =VLOOKUP(A12,'Unit COGS'!$A$23:$B$35,2,FALSE) | C12: 0 | D12: =B12*C12 | E12: 1 | F12: =B12*E12 | G12: =VLOOKUP(A12,Credits!$A$5:$C$17,3,FALSE) | H12: =E12*G12
A13: Social captions | B13: =VLOOKUP(A13,'Unit COGS'!$A$23:$B$35,2,FALSE) | C13: 1 | D13: =B13*C13 | E13: 1 | F13: =B13*E13 | G13: =VLOOKUP(A13,Credits!$A$5:$C$17,3,FALSE) | H13: =E13*G13
A14: Web export | B14: =VLOOKUP(A14,'Unit COGS'!$A$23:$B$35,2,FALSE) | C14: 1 | D14: =B14*C14 | E14: 2 | F14: =B14*E14 | G14: =VLOOKUP(A14,Credits!$A$5:$C$17,3,FALSE) | H14: =E14*G14
A15: Storage | B15: =VLOOKUP(A15,'Unit COGS'!$A$23:$B$35,2,FALSE) | C15: 1 | D15: =B15*C15 | E15: 1 | F15: =B15*E15 | G15: =VLOOKUP(A15,Credits!$A$5:$C$17,3,FALSE) | H15: =E15*G15
A16: TOTAL | D16: =SUM(D5:D15) | F16: =SUM(F5:F15) | H16: =SUM(H5:H15)
A18: Credits for a clean first-pass video | B18: =SUMPRODUCT($C$5:$C$15,$G$5:$G$15)
A19: COGS per credit (drives plan margins) | B19: ='Per Video'!$D$16/'Per Video'!$B$18
A20: Effective markup on a full video | B20: ='Per Video'!$B$18*Assumptions!$B$8/'Per Video'!$D$16
A22: Photo analysis on GPT-4o vision is the single largest line. See the Optimisations sheet.

Sheet Credits
A1: Credit price list
A2: What each action costs the user. Credits are set at roughly the target markup over COGS.
A4: Action | B4: COGS ₹ | C4: Credits | D4: Retail ₹ | E4: Multiple | F4: Margin % | G4: Basis
A5: Extract facts | B5: =VLOOKUP(A5,'Unit COGS'!$A$23:$B$35,2,FALSE) | C5: 2 | D5: =C5*Assumptions!$B$8 | E5: =IF(B5=0,"—",D5/B5) | F5: =IF(D5=0,"—",(D5-B5)/D5) | G5: Flat.
A6: Script pack | B6: =VLOOKUP(A6,'Unit COGS'!$A$23:$B$35,2,FALSE) | C6: 4 | D6: =C6*Assumptions!$B$8 | E6: =IF(B6=0,"—",D6/B6) | F6: =IF(D6=0,"—",(D6-B6)/D6) | G6: Three variations in one click.
A7: Refine script | B7: =VLOOKUP(A7,'Unit COGS'!$A$23:$B$35,2,FALSE) | C7: 1 | D7: =C7*Assumptions!$B$8 | E7: =IF(B7=0,"—",D7/B7) | F7: =IF(D7=0,"—",(D7-B7)/D7) | G7: Per rewrite.
A8: Photo analysis | B8: =VLOOKUP(A8,'Unit COGS'!$A$23:$B$35,2,FALSE) | C8: 1 | D8: =C8*Assumptions!$B$8 | E8: =IF(B8=0,"—",D8/B8) | F8: =IF(D8=0,"—",(D8-B8)/D8) | G8: Per photo. Consider free if you move to 4o-mini.
A9: Voiceover | B9: =VLOOKUP(A9,'Unit COGS'!$A$23:$B$35,2,FALSE) | C9: =ROUNDUP(Assumptions!$B$10/15,0)*3 | D9: =C9*Assumptions!$B$8 | E9: =IF(B9=0,"—",D9/B9) | F9: =IF(D9=0,"—",(D9-B9)/D9) | G9: 3 credits per 15s — scales with script length.
A10: Voice preview | B10: =VLOOKUP(A10,'Unit COGS'!$A$23:$B$35,2,FALSE) | C10: 1 | D10: =C10*Assumptions!$B$8 | E10: =IF(B10=0,"—",D10/B10) | F10: =IF(D10=0,"—",(D10-B10)/D10) | G10: Per sample.
A11: Subtitle re-align | B11: =VLOOKUP(A11,'Unit COGS'!$A$23:$B$35,2,FALSE) | C11: 1 | D11: =C11*Assumptions!$B$8 | E11: =IF(B11=0,"—",D11/B11) | F11: =IF(D11=0,"—",(D11-B11)/D11) | G11: Re-sync only, no new audio.
A12: Subtitle translate | B12: =VLOOKUP(A12,'Unit COGS'!$A$23:$B$35,2,FALSE) | C12: 4 | D12: =C12*Assumptions!$B$8 | E12: =IF(B12=0,"—",D12/B12) | F12: =IF(D12=0,"—",(D12-B12)/D12) | G12: Per target language.
A13: AI auto-edit | B13: =VLOOKUP(A13,'Unit COGS'!$A$23:$B$35,2,FALSE) | C13: 10 | D13: =C13*Assumptions!$B$8 | E13: =IF(B13=0,"—",D13/B13) | F13: =IF(D13=0,"—",(D13-B13)/D13) | G13: Builds the whole timeline.
A14: Social captions | B14: =VLOOKUP(A14,'Unit COGS'!$A$23:$B$35,2,FALSE) | C14: 2 | D14: =C14*Assumptions!$B$8 | E14: =IF(B14=0,"—",D14/B14) | F14: =IF(D14=0,"—",(D14-B14)/D14) | G14: IG + FB + WhatsApp pack.
A15: Web export | B15: =VLOOKUP(A15,'Unit COGS'!$A$23:$B$35,2,FALSE) | C15: 8 | D15: =C15*Assumptions!$B$8 | E15: =IF(B15=0,"—",D15/B15) | F15: =IF(D15=0,"—",(D15-B15)/D15) | G15: 1080p up to 60s. +4 per extra 30s.
A16: Storage | B16: =VLOOKUP(A16,'Unit COGS'!$A$23:$B$35,2,FALSE) | C16: 0 | D16: =C16*Assumptions!$B$8 | E16: =IF(B16=0,"—",D16/B16) | F16: =IF(D16=0,"—",(D16-B16)/D16) | G16: Absorbed — never billed separately.
A17: Desktop export | B17: 0 | C17: 0 | D17: =C17*Assumptions!$B$8 | E17: =IF(B17=0,"—",D17/B17) | F17: =IF(D17=0,"—",(D17-B17)/D17) | G17: Renders on the user's own GPU. Costs you nothing.
A19: FREE — never metered
A20: Uploading photos and video
A21: Every timeline edit: trim, transitions, text overlays, Ken Burns
A22: Playback, preview and scrubbing
A23: Saving and autosave
A24: Kannada transliteration typing
A25: Font and sound-effect search
A26: Brand kit
A27: Duplicating a project
A28: Re-downloading a video you already exported
A29: Publishing to social
A30: Any action that fails — refunded automatically
A31: Regenerating an identical script + voice + style (served from cache)

Sheet Plans
A1: Plans and margins
A2: Prices are GST-inclusive. Margin shown at 100% credit burn and at the expected burn rate.
A4: Plan | B4: ₹ / month | C4: Credits | D4: Videos (clean run) | E4: Videos (with rework) | F4: Ex-GST revenue | G4: Gateway fee | H4: Net revenue | I4: COGS @100% burn | J4: Margin @100% | K4: COGS @ expected burn | L4: Margin @ expected
A5: Free | B5: 0 | C5: 60 | D5: =C5/'Per Video'!$B$18 | E5: =C5/'Per Video'!$H$16 | F5: =B5/(1+Assumptions!$B$6) | G5: =B5*Assumptions!$B$7 | H5: =F5-G5 | I5: =C5*'Per Video'!$B$19 | J5: =IF(H5=0,"—",(H5-I5)/H5) | K5: =C5*'Per Video'!$B$19*Assumptions!$B$23 | L5: =IF(H5=0,"—",(H5-K5)/H5)
A6: Starter | B6: 599 | C6: 500 | D6: =C6/'Per Video'!$B$18 | E6: =C6/'Per Video'!$H$16 | F6: =B6/(1+Assumptions!$B$6) | G6: =B6*Assumptions!$B$7 | H6: =F6-G6 | I6: =C6*'Per Video'!$B$19 | J6: =IF(H6=0,"—",(H6-I6)/H6) | K6: =C6*'Per Video'!$B$19*Assumptions!$B$23 | L6: =IF(H6=0,"—",(H6-K6)/H6)
A7: Pro | B7: 1499 | C7: 1600 | D7: =C7/'Per Video'!$B$18 | E7: =C7/'Per Video'!$H$16 | F7: =B7/(1+Assumptions!$B$6) | G7: =B7*Assumptions!$B$7 | H7: =F7-G7 | I7: =C7*'Per Video'!$B$19 | J7: =IF(H7=0,"—",(H7-I7)/H7) | K7: =C7*'Per Video'!$B$19*Assumptions!$B$23 | L7: =IF(H7=0,"—",(H7-K7)/H7)
A8: Studio | B8: 3999 | C8: 5000 | D8: =C8/'Per Video'!$B$18 | E8: =C8/'Per Video'!$H$16 | F8: =B8/(1+Assumptions!$B$6) | G8: =B8*Assumptions!$B$7 | H8: =F8-G8 | I8: =C8*'Per Video'!$B$19 | J8: =IF(H8=0,"—",(H8-I8)/H8) | K8: =C8*'Per Video'!$B$19*Assumptions!$B$23 | L8: =IF(H8=0,"—",(H8-K8)/H8)
A10: TOP-UPS (credits never expire; monthly credits do)
A11: Pack | B11: ₹ | C11: Credits | E11: Ex-GST revenue | F11: Gateway fee | G11: Net revenue | H11: COGS @100% | I11: Margin @100%
A12: Small | B12: 299 | C12: 250 | E12: =B12/(1+Assumptions!$B$6) | F12: =B12*Assumptions!$B$7 | G12: =E12-F12 | H12: =C12*'Per Video'!$B$19 | I12: =(G12-H12)/G12
A13: Large | B13: 799 | C13: 750 | E13: =B13/(1+Assumptions!$B$6) | F13: =B13*Assumptions!$B$7 | G13: =E13-F13 | H13: =C13*'Per Video'!$B$19 | I13: =(G13-H13)/G13
A16: Annual pricing = 10 months (two free): ₹5,990 / ₹14,990 / ₹39,990.
A17: Free plan is an acquisition cost, not a loss to fix — cap it at 720p with a watermark.
A18: Every paid tier includes unlimited desktop exports — zero marginal cost, and no browser competitor can match it.

Sheet Fixed Costs
A1: Fixed monthly infrastructure
A2: Sized for ~500 monthly active users / ~200 paying.
A4: Service | B4: Purpose | C4: USD / month | D4: INR / month
A5: Vercel Pro | B5: Next.js hosting | C5: 20 | D5: =C5*Assumptions!$B$5
A6: Supabase Pro | B6: Postgres, backups, connection pooling | C6: 25 | D6: =C6*Assumptions!$B$5
A7: Clerk | B7: Auth — free below 10k MAU, then $25 | C7: 0 | D7: =C7*Assumptions!$B$5
A8: Redis (Railway/Upstash) | B8: Job queue for exports | C8: 10 | D8: =C8*Assumptions!$B$5
A9: Render worker | B9: 4 vCPU dedicated box for Remotion/FFmpeg | C9: 40 | D9: =C9*Assumptions!$B$5
A10: Cloudflare R2 | B10: Media + export storage, free egress | C10: 5 | D10: =C10*Assumptions!$B$5
A11: Domain, email, monitoring | B11: Sentry, Resend, DNS | C11: 15 | D11: =C11*Assumptions!$B$5
A12: TOTAL | C12: =SUM(C5:C11) | D12: =SUM(D5:D11)
A14: Fixed cost per paying user | B14: ='Fixed Costs'!$D$12/Assumptions!$B$24

Sheet P&L
A1: Monthly P&L scenario
A2: Change the user counts (yellow) to model any mix.
A4: Plan | B4: Users | C4: ₹ / month | D4: Gross revenue | E4: Net revenue | F4: Credit COGS | G4: Contribution
A5: Free | B5: 400 | C5: =Plans!B5 | D5: =B5*C5 | E5: =B5*Plans!H5 | F5: =B5*Plans!K5 | G5: =E5-F5
A6: Starter | B6: 120 | C6: =Plans!B6 | D6: =B6*C6 | E6: =B6*Plans!H6 | F6: =B6*Plans!K6 | G6: =E6-F6
A7: Pro | B7: 65 | C7: =Plans!B7 | D7: =B7*C7 | E7: =B7*Plans!H7 | F7: =B7*Plans!K7 | G7: =E7-F7
A8: Studio | B8: 15 | C8: =Plans!B8 | D8: =B8*C8 | E8: =B8*Plans!H8 | F8: =B8*Plans!K8 | G8: =E8-F8
A9: TOTAL | B9: =SUM(B5:B8) | C9: =SUM(C5:C8) | D9: =SUM(D5:D8) | E9: =SUM(E5:E8) | F9: =SUM(F5:F8) | G9: =SUM(G5:G8)
A11: Gross contribution | B11: ='P&L'!$G$9
A12: Fixed infrastructure | B12: =-'Fixed Costs'!$D$12
A13: Monthly profit | B13: ='P&L'!$G$9-'Fixed Costs'!$D$12
A14: Net margin | B14: =IF('P&L'!$E$9=0,"—",('P&L'!$G$9-'Fixed Costs'!$D$12)/'P&L'!$E$9)
A16: Break-even paying users (current mix ratio) | B16: =IF('P&L'!$G$9=0,"—",ROUNDUP('Fixed Costs'!$D$12/('P&L'!$G$9/SUM(B6:B8)),0))

Sheet Optimisations
A1: Cost reductions available before launch
A2: These change the COGS numbers on every other sheet. Ranked by saving per video.
A4: Change | B4: Where | C4: Saving ₹ | D4: Applies to | E4: Effort
A5: Photo analysis → gpt-4o-mini | B5: src/lib/ai/client.ts — visionModel | C5: =(VLOOKUP("Photo analysis",'Unit COGS'!$A$23:$B$35,2,FALSE)-VLOOKUP("Photo analysis (4o-mini alt)",'Unit COGS'!$A$23:$B$35,2,FALSE))*Assumptions!$B$11 | D5: Clean run | E5: One line
A6: AI auto-edit → Gemini primary, GPT-4o fallback | B6: lib/timeline/generate-ai.ts | C6: =VLOOKUP("AI auto-edit",'Unit COGS'!$A$23:$B$35,2,FALSE)*0.9 | D6: Clean run | E6: Mirror the generate-script pattern
A7: Remove duplicate TTS normalisation | B7: synthesize-voiceover.ts Phase 1 + google-cloud-tts.ts both run | C7: =VLOOKUP("Voiceover",'Unit COGS'!$A$23:$B$35,2,FALSE)*0.045 | D7: Clean run | E7: Delete one — also cuts latency
A8: Cache TTS on hash(script+voice+style) | B8: New cache table + R2 key | C8: =VLOOKUP("Voiceover",'Unit COGS'!$A$23:$B$35,2,FALSE)*('Per Video'!E10-1) | D8: Rework only | E8: Kills the top burn source
A9: Subtitle translate → Gemini primary | B9: api/projects/[id]/subtitles/translate/route.ts | C9: =VLOOKUP("Subtitle translate",'Unit COGS'!$A$23:$B$35,2,FALSE)*0.78 | D9: Not in reference video | E9: Fallback already written
A10: SAVING ON A CLEAN RUN | C10: =SUMIF($D$5:$D$9,"Clean run",$C$5:$C$9)
A11: ADDITIONAL SAVING ON A REWORKED VIDEO | C11: =SUMIF($D$5:$D$9,"Rework only",$C$5:$C$9)
A13: Clean-run COGS today | B13: ='Per Video'!$D$16
A14: Clean-run COGS after these changes | B14: ='Per Video'!$D$16-SUMIF($D$5:$D$9,"Clean run",$C$5:$C$9)
A15: Markup at unchanged retail prices | B15: ='Per Video'!$B$18*Assumptions!$B$8/('Per Video'!$D$16-SUMIF($D$5:$D$9,"Clean run",$C$5:$C$9))
A16: Reworked-video COGS today | B16: ='Per Video'!$F$16
A17: Reworked-video COGS after these changes | B17: ='Per Video'!$F$16-SUMIF($D$5:$D$9,"Clean run",$C$5:$C$9)-SUMIF($D$5:$D$9,"Rework only",$C$5:$C$9)
A19: Savings are scoped deliberately: TTS caching only pays back on regeneration, and subtitle translate is not part of the reference video at all. Subtracting either from the clean-run baseline would overstate the gain.

Sheet User-Facing
A1: What the customer sees
A2: One price per button. Internal fan-out — normalisation, TTS, alignment, fallbacks — is invisible and included.
A4: Button | B4: Where | C4: What the user reads | D4: Credits
A5: Extract facts | B5: Details tab | C5: Read the listing and pull out the facts | D5: =VLOOKUP("Extract facts",Credits!$A$5:$C$17,3,FALSE)
A6: Generate scripts | B6: Scripts tab | C6: Write 3 script options | D6: =VLOOKUP("Script pack",Credits!$A$5:$C$17,3,FALSE)
A7: Refine with AI | B7: Scripts tab | C7: Rewrite this script with your notes | D7: =VLOOKUP("Refine script",Credits!$A$5:$C$17,3,FALSE)
A8: Analyze (per photo) | B8: Media tab | C8: Tag this photo for auto-editing | D8: =VLOOKUP("Photo analysis",Credits!$A$5:$C$17,3,FALSE)
A9: Analyze all | B9: Media tab | C9: Tag every photo in the project | D9: =VLOOKUP("Photo analysis",Credits!$A$5:$C$17,3,FALSE)*Assumptions!$B$11
A10: Preview sample | B10: Voiceover panel | C10: Hear this voice before committing | D10: =VLOOKUP("Voice preview",Credits!$A$5:$C$17,3,FALSE)
A11: Generate voiceover | B11: Voiceover panel | C11: Narrate the script | D11: =VLOOKUP("Voiceover",Credits!$A$5:$C$17,3,FALSE)
A12: AI auto-edit | B12: Timeline panel | C12: Build the timeline from your photos + script | D12: =VLOOKUP("AI auto-edit",Credits!$A$5:$C$17,3,FALSE)
A13: Translate subtitles | B13: Subtitle Studio | C13: Translate captions to another language | D13: =VLOOKUP("Subtitle translate",Credits!$A$5:$C$17,3,FALSE)
A14: Re-time subtitles | B14: Subtitle Studio | C14: Re-sync captions to the audio | D14: =VLOOKUP("Subtitle re-align",Credits!$A$5:$C$17,3,FALSE)
A15: Generate content pack | B15: Social tab | C15: Instagram, Facebook and WhatsApp captions | D15: =VLOOKUP("Social captions",Credits!$A$5:$C$17,3,FALSE)
A16: Export | B16: Editor top nav (web) | C16: Render 1080p MP4 | D16: =VLOOKUP("Web export",Credits!$A$5:$C$17,3,FALSE)
A17: Export | B17: Desktop app | C17: Renders on your PC — unlimited | D17: =VLOOKUP("Desktop export",Credits!$A$5:$C$17,3,FALSE)
A19: THE THREE NUMBERS ON THE PRICING PAGE
A20: 1 credit ≈ | B20: =Assumptions!$B$8
A21: A finished video ≈ (credits) | B21: ='Per Video'!$B$18
A22: Pro = ₹1,499 for ~N videos | B22: =Plans!D7
A24: UI RULES
A25: Price on the button before the click — "Generate voiceover · 9 cr". Variable costs computed live.
A26: Confirm only above 10 credits (AI auto-edit, bulk photo analysis). Nothing smaller needs a dialog.
A27: Receipt toast on completion: "Voiceover ready · 9 credits used · 1,562 left".
A28: Persistent balance in the top nav, clickable through to history.
A29: History page in Settings: date, action, project, credits, running balance — refunds as their own rows.
A30: Low balance at 15% — inline banner, not a modal. At zero, disable paid buttons with a top-up prompt.
A31: Never charge twice for the same output — unchanged regeneration is free and the button says so.
